odoo/addons/product_pricelist_direct_print/README.rst
odoo/addons/product_pricelist_direct_print/__init__.py
odoo/addons/product_pricelist_direct_print/__manifest__.py
odoo/addons/product_pricelist_direct_print/data/mail_template_data.xml
odoo/addons/product_pricelist_direct_print/i18n/ca.po
odoo/addons/product_pricelist_direct_print/i18n/es.po
odoo/addons/product_pricelist_direct_print/i18n/fr.po
odoo/addons/product_pricelist_direct_print/i18n/it.po
odoo/addons/product_pricelist_direct_print/i18n/product_pricelist_direct_print.pot
odoo/addons/product_pricelist_direct_print/readme/CONFIGURE.rst
odoo/addons/product_pricelist_direct_print/readme/CONTRIBUTORS.rst
odoo/addons/product_pricelist_direct_print/readme/DESCRIPTION.rst
odoo/addons/product_pricelist_direct_print/readme/USAGE.rst
odoo/addons/product_pricelist_direct_print/report/__init__.py
odoo/addons/product_pricelist_direct_print/report/product_pricelist_xlsx.py
odoo/addons/product_pricelist_direct_print/report/product_pricelist_xlsx.xml
odoo/addons/product_pricelist_direct_print/static/description/icon.png
odoo/addons/product_pricelist_direct_print/static/description/index.html
odoo/addons/product_pricelist_direct_print/tests/__init__.py
odoo/addons/product_pricelist_direct_print/tests/test_product_pricelist_direct_print.py
odoo/addons/product_pricelist_direct_print/views/report_product_pricelist.xml
odoo/addons/product_pricelist_direct_print/wizards/__init__.py
odoo/addons/product_pricelist_direct_print/wizards/product_pricelist_print.py
odoo/addons/product_pricelist_direct_print/wizards/product_pricelist_print_view.xml
odoo12_addon_product_pricelist_direct_print-12.0.2.1.0.dist-info/METADATA
odoo12_addon_product_pricelist_direct_print-12.0.2.1.0.dist-info/WHEEL
odoo12_addon_product_pricelist_direct_print-12.0.2.1.0.dist-info/top_level.txt
odoo12_addon_product_pricelist_direct_print-12.0.2.1.0.dist-info/RECORD
