Metadata-Version: 2.1
Name: odoo12-addon-product-pricelist-direct-print
Version: 12.0.2.1.0
Summary: Print price list from menu option, product templates, products variants or price lists
Home-page: https://github.com/OCA/product-attribute
Author: Tecnativa, Odoo Community Association (OCA)
Author-email: support@odoo-community.org
License: AGPL-3
Platform: UNKNOWN
Classifier: Programming Language :: Python
Classifier: Framework :: Odoo
Classifier: Framework :: Odoo :: 12.0
Classifier: License :: OSI Approved :: GNU Affero General Public License v3
Requires-Python: >=3.5
Requires-Dist: odoo12-addon-report-xlsx
Requires-Dist: odoo (<12.1dev,>=12.0a)
